markd2pdf/__init__.py
markd2pdf/cli.py
markd2pdf/py.typed
markd2pdf/styles/dracula.css
markd2pdf/styles/github_dark.css
markd2pdf/styles/minimal_light.css
markd2pdf/styles/nord.css
markd2pdf/styles/professional_dark.css
markd2pdf-0.1.1.dist-info/METADATA
markd2pdf-0.1.1.dist-info/WHEEL
markd2pdf-0.1.1.dist-info/entry_points.txt
markd2pdf-0.1.1.dist-info/licenses/LICENSE
markd2pdf-0.1.1.dist-info/RECORD
