Metadata-Version: 2.4
Name: markd2pdf
Version: 0.1.1
Summary: Convert Markdown files to beautifully styled PDFs
Project-URL: Homepage, https://github.com/ramcharan/markd2pdf
Project-URL: Repository, https://github.com/ramcharan/markd2pdf
Project-URL: Issues, https://github.com/ramcharan/markd2pdf/issues
Author: Ramcharan
License-Expression: MIT
License-File: LICENSE
Keywords: cli,converter,documentation,markdown,pdf
Classifier: Development Status :: 4 - Beta
Classifier: Environment :: Console
Classifier: Intended Audience :: Developers
Classifier: Intended Audience :: End Users/Desktop
Classifier: License :: OSI Approved :: MIT License
Classifier: Operating System :: OS Independent
Classifier: Programming Language :: Python :: 3
Classifier: Programming Language :: Python :: 3.12
Classifier: Programming Language :: Python :: 3.13
Classifier: Topic :: Documentation
Classifier: Topic :: Text Processing :: Markup :: Markdown
Classifier: Topic :: Utilities
Classifier: Typing :: Typed
Requires-Python: >=3.12
Requires-Dist: markdown>=3.7
Requires-Dist: pygments>=2.18.0
Requires-Dist: rich>=13.9.0
Requires-Dist: typer>=0.12.0
Requires-Dist: weasyprint>=62.0
